python_sn2-0.4.0.dist-info/licenses/LICENSE
sn2/__init__.py
sn2/constants.py
sn2/data_model.py
sn2/device.py
sn2/py.typed
python_sn2-0.4.0.dist-info/METADATA
python_sn2-0.4.0.dist-info/WHEEL
python_sn2-0.4.0.dist-info/top_level.txt
python_sn2-0.4.0.dist-info/RECORD
