Metadata-Version: 2.4
Name: python-sn2
Version: 0.4.0
Summary: Python library for SystemNexa2 device integration
Author: Claes Nordmark
License: MIT
Project-URL: Homepage, https://github.com/konsulten/python-sn2
Project-URL: Repository, https://github.com/konsulten/python-sn2
Project-URL: Issues, https://github.com/konsulten/python-sn2/issues
Keywords: systemnexa,home automation,iot
Classifier: Development Status :: 3 - Alpha
Classifier: Intended Audience :: Developers
Classifier: License :: OSI Approved :: MIT License
Classifier: Programming Language :: Python :: 3.12
Classifier: Programming Language :: Python :: 3.13
Requires-Python: >=3.12
License-File: LICENSE
Requires-Dist: aiohttp>=3.13.2
Requires-Dist: websockets>=15.0.1
Provides-Extra: dev
Requires-Dist: bump-my-version>=0.16.0; extra == "dev"
Requires-Dist: pytest==8.4.2; extra == "dev"
Requires-Dist: pytest-asyncio==1.2.0; extra == "dev"
Requires-Dist: pytest-cov>=7.0.0; extra == "dev"
Requires-Dist: ruff==0.14.2; extra == "dev"
Requires-Dist: uv==0.9.18; extra == "dev"
Dynamic: license-file
